zitro1992_gamedev/__init__.py
zitro1992_gamedev/common.py
zitro1992_gamedev/first_person_shooter.py
zitro1992_gamedev-0.1.6.dist-info/METADATA
zitro1992_gamedev-0.1.6.dist-info/WHEEL
zitro1992_gamedev-0.1.6.dist-info/RECORD
