Metadata-Version: 2.1
Name: zitro1992-gamedev
Version: 0.1.6
Summary: Game Development Package
Author: Kevin ortiz
Author-email: ncs.kevin.ortiz@gmail.com
Requires-Python: >=3.9,<4.0
Classifier: Programming Language :: Python :: 3
Classifier: Programming Language :: Python :: 3.9
Classifier: Programming Language :: Python :: 3.10
Classifier: Programming Language :: Python :: 3.11
Classifier: Programming Language :: Python :: 3.12
